della/cli.py
della/command_parser.py
della/completion.py
della/constants.py
della/default_config.py
della/della.py
della/init_tasks.py
della/task.py
della_tasks-0.1.0.dist-info/LICENSE.md
della_tasks-0.1.0.dist-info/METADATA
della_tasks-0.1.0.dist-info/WHEEL
della_tasks-0.1.0.dist-info/entry_points.txt
della_tasks-0.1.0.dist-info/RECORD
