Metadata-Version: 2.1
Name: della-tasks
Version: 0.1.0
Summary: Top-level package for Della.
Home-page: https://github.com/keagud/della
License: BSD-3-Clause
Author: Keaton Guderian
Author-email: keagud@protonmail.com
Requires-Python: >=3.10,<4
Classifier: License :: OSI Approved :: BSD License
Classifier: Natural Language :: English
Classifier: Programming Language :: Python :: 3
Classifier: Programming Language :: Python :: 3.10
Classifier: Programming Language :: Python :: 3.11
Classifier: Programming Language :: Python :: 3
Classifier: Programming Language :: Python :: 3.10
Classifier: Programming Language :: Python :: 3.11
Classifier: Programming Language :: Python :: 3.8
Classifier: Programming Language :: Python :: 3.9
Requires-Dist: argparse (>=1.4.0,<2.0.0)
Requires-Dist: dateparse (>=1.0.0,<2.0.0)
Requires-Dist: getchoice
Requires-Dist: halo (>=0.0.31,<0.0.32)
Requires-Dist: paramiko (>=3.1.0,<4.0.0)
Requires-Dist: prompt-toolkit (>=3.0.38,<4.0.0)
Requires-Dist: python-slugify (>=8.0.1,<9.0.0)
Requires-Dist: toml (>=0.10.2,<0.11.0)
